wsc_influx_tools/__init__.py
wsc_influx_tools/wsc_influx_get_data.py
wsc_influx_tools/wsc_influx_send_data.py
wsc_influx_tools-2023.1.0.dist-info/METADATA
wsc_influx_tools-2023.1.0.dist-info/WHEEL
wsc_influx_tools-2023.1.0.dist-info/entry_points.txt
wsc_influx_tools-2023.1.0.dist-info/top_level.txt
wsc_influx_tools-2023.1.0.dist-info/RECORD
