Metadata-Version: 2.1
Name: wsc-influx-tools
Version: 2023.1.0
Summary: "Bridgestone World Solar Challenge Influx Tools"
Home-page: https://github.com/worldsolarchallenge/wsc-influx-tools
Author: "David Snowdon"
Author-email: "pypi@snowdon.id.au"
Maintainer: "David Snowdon"
Maintainer-email: "pypi@snowdon.id.au"
License: "BSD 3-Clause License"
Project-URL: Source, https://github.com/worldsolarchallenge/wsc-influx-tools
Project-URL: Tracker, https://github.com/worldsolarchallenge/wsc-influx-tools/issues
Project-URL: Documentation, https://github.com/worldsolarchallenge/wsc-influx-tools
Keywords: pytest,eos
Classifier: License :: OSI Approved :: BSD License
Classifier: Operating System :: OS Independent
Classifier: Programming Language :: Python :: 3
Classifier: Framework :: Pytest
Classifier: Intended Audience :: Developers
Classifier: Topic :: Software Development :: Testing
Requires-Dist: influxdb3-python
Requires-Dist: influxdb-client
Requires-Dist: pandas
Requires-Dist: pyyaml
Requires-Dist: requests
Requires-Dist: mergedeep
